{"expiry":1699514666,"data":[{"type":"constructor","inputs":[],"stateMutability":"nonpayable","payable":null},{"type":"function","name":"AUTHORS","inputs":[],"outputs":[{"name":"","type":"string","internalType":"string"}],"stateMutability":"view","payable":null},{"type":"function","name":"DAYS_IN_YEAR","inputs":[],"outputs":[{"name":"","type":"uint256","internalType":"uint256"}],"stateMutability":"view","payable":null},{"type":"function","name":"EAA_PM_START","inputs":[],"outputs":[{"name":"","type":"uint256","internalType":"uint256"}],"stateMutability":"view","payable":null},{"type":"function","name":"EAA_PM_STEP","inputs":[],"outputs":[{"name":"","type":"uint256","internalType":"uint256"}],"stateMutability":"view","payable":null},{"type":"function","name":"EAA_RANK_STEP","inputs":[],"outputs":[{"name":"","type":"uint256","internalType":"uint256"}],"stateMutability":"view","payable":null},{"type":"function","name":"GENESIS_RANK","inputs":[],"outputs":[{"name":"","type":"uint256","internalType":"uint256"}],"stateMutability":"view","payable":null},{"type":"function","name":"MAX_PENALTY_PCT","inputs":[],"outputs":[{"name":"","type":"uint256","internalType":"uint256"}],"stateMutability":"view","payable":null},{"type":"function","name":"MAX_TERM_END","inputs":[],"outputs":[{"name":"","type":"uint256","internalType":"uint256"}],"stateMutability":"view","payable":null},{"type":"function","name":"MAX_TERM_START","inputs":[],"outputs":[{"name":"","type":"uint256","internalType":"uint256"}],"stateMutability":"view","payable":null},{"type":"function","name":"MIN_TERM","inputs":[],"outputs":[{"name":"","type":"uint256","internalType":"uint256"}],"stateMutability":"view","payable":null},{"type":"function","name":"REWARD_AMPLIFIER_END","inputs":[],"outputs":[{"name":"","type":"uint256","internalType":"uint256"}],"stateMutability":"view","payable":null},{"type":"function","name":"REWARD_AMPLIFIER_START","inputs":[],"outputs":[{"name":"","type":"uint256","internalType":"uint256"}],"stateMutability":"view","payable":null},{"type":"function","name":"SECONDS_IN_DAY","inputs":[],"outputs":[{"name":"","type":"uint256","internalType":"uint256"}],"stateMutability":"view","payable":null},{"type":"function","name":"TERM_AMPLIFIER","inputs":[],"outputs":[{"name":"","type":"uint256","internalType":"uint256"}],"stateMutability":"view","payable":null},{"type":"function","name":"TERM_AMPLIFIER_THRESHOLD","inputs":[],"outputs":[{"name":"","type":"uint256","internalType":"uint256"}],"stateMutability":"view","payable":null},{"type":"function","name":"WITHDRAWAL_WINDOW_DAYS","inputs":[],"outputs":[{"name":"","type":"uint256","internalType":"uint256"}],"stateMutability":"view","payable":null},{"type":"function","name":"XEN_APY_DAYS_STEP","inputs":[],"outputs":[{"name":"","type":"uint256","internalType":"uint256"}],"stateMutability":"view","payable":null},{"type":"function","name":"XEN_APY_END","inputs":[],"outputs":[{"name":"","type":"uint256","internalType":"uint256"}],"stateMutability":"view","payable":null},{"type":"function","name":"XEN_APY_START","inputs":[],"outputs":[{"name":"","type":"uint256","internalType":"uint256"}],"stateMutability":"view","payable":null},{"type":"function","name":"XEN_MIN_BURN","inputs":[],"outputs":[{"name":"","type":"uint256","internalType":"uint256"}],"stateMutability":"view","payable":null},{"type":"function","name":"XEN_MIN_STAKE","inputs":[],"outputs":[{"name":"","type":"uint256","internalType":"uint256"}],"stateMutability":"view","payable":null},{"type":"function","name":"activeMinters","inputs":[],"outputs":[{"name":"","type":"uint256","internalType":"uint256"}],"stateMutability":"view","payable":null},{"type":"function","name":"activeStakes","inputs":[],"outputs":[{"name":"","type":"uint256","internalType":"uint256"}],"stateMutability":"view","payable":null},{"type":"function","name":"allowance","inputs":[{"name":"owner","type":"address","internalType":"address"},{"name":"spender","type":"address","internalType":"address"}],"outputs":[{"name":"","type":"uint256","internalType":"uint256"}],"stateMutability":"view","payable":null},{"type":"function","name":"approve","inputs":[{"name":"spender","type":"address","internalType":"address"},{"name":"amount","type":"uint256","internalType":"uint256"}],"outputs":[{"name":"","type":"bool","internalType":"bool"}],"stateMutability":"nonpayable","payable":null},{"type":"function","name":"balanceOf","inputs":[{"name":"account","type":"address","internalType":"address"}],"outputs":[{"name":"","type":"uint256","internalType":"uint256"}],"stateMutability":"view","payable":null},{"type":"function","name":"burn","inputs":[{"name":"user","type":"address","internalType":"address"},{"name":"amount","type":"uint256","internalType":"uint256"}],"outputs":[],"stateMutability":"nonpayable","payable":null},{"type":"function","name":"claimMintReward","inputs":[],"outputs":[],"stateMutability":"nonpayable","payable":null},{"type":"function","name":"claimMintRewardAndShare","inputs":[{"name":"other","type":"address","internalType":"address"},{"name":"pct","type":"uint256","internalType":"uint256"}],"outputs":[],"stateMutability":"nonpayable","payable":null},{"type":"function","name":"claimMintRewardAndStake","inputs":[{"name":"pct","type":"uint256","internalType":"uint256"},{"name":"term","type":"uint256","internalType":"uint256"}],"outputs":[],"stateMutability":"nonpayable","payable":null},{"type":"function","name":"claimRank","inputs":[{"name":"term","type":"uint256","internalType":"uint256"}],"outputs":[],"stateMutability":"nonpayable","payable":null},{"type":"function","name":"decimals","inputs":[],"outputs":[{"name":"","type":"uint8","internalType":"uint8"}],"stateMutability":"view","payable":null},{"type":"function","name":"decreaseAllowance","inputs":[{"name":"spender","type":"address","internalType":"address"},{"name":"subtractedValue","type":"uint256","internalType":"uint256"}],"outputs":[{"name":"","type":"bool","internalType":"bool"}],"stateMutability":"nonpayable","payable":null},{"type":"function","name":"genesisTs","inputs":[],"outputs":[{"name":"","type":"uint256","internalType":"uint256"}],"stateMutability":"view","payable":null},{"type":"function","name":"getCurrentAMP","inputs":[],"outputs":[{"name":"","type":"uint256","internalType":"uint256"}],"stateMutability":"view","payable":null},{"type":"function","name":"getCurrentAPY","inputs":[],"outputs":[{"name":"","type":"uint256","internalType":"uint256"}],"stateMutability":"view","payable":null},{"type":"function","name":"getCurrentEAAR","inputs":[],"outputs":[{"name":"","type":"uint256","internalType":"uint256"}],"stateMutability":"view","payable":null},{"type":"function","name":"getCurrentMaxTerm","inputs":[],"outputs":[{"name":"","type":"uint256","internalType":"uint256"}],"stateMutability":"view","payable":null},{"type":"function","name":"getGrossReward","inputs":[{"name":"rankDelta","type":"uint256","internalType":"uint256"},{"name":"amplifier","type":"uint256","internalType":"uint256"},{"name":"term","type":"uint256","internalType":"uint256"},{"name":"eaa","type":"uint256","internalType":"uint256"}],"outputs":[{"name":"","type":"uint256","internalType":"uint256"}],"stateMutability":"pure","payable":null},{"type":"function","name":"getUserMint","inputs":[],"outputs":[{"name":"","type":"tuple","internalType":"struct XENCrypto.MintInfo","components":[{"name":"user","type":"address","internalType":"address"},{"name":"term","type":"uint256","internalType":"uint256"},{"name":"maturityTs","type":"uint256","internalType":"uint256"},{"name":"rank","type":"uint256","internalType":"uint256"},{"name":"amplifier","type":"uint256","internalType":"uint256"},{"name":"eaaRate","type":"uint256","internalType":"uint256"}]}],"stateMutability":"view","payable":null},{"type":"function","name":"getUserStake","inputs":[],"outputs":[{"name":"","type":"tuple","internalType":"struct XENCrypto.StakeInfo","components":[{"name":"term","type":"uint256","internalType":"uint256"},{"name":"maturityTs","type":"uint256","internalType":"uint256"},{"name":"amount","type":"uint256","internalType":"uint256"},{"name":"apy","type":"uint256","internalType":"uint256"}]}],"stateMutability":"view","payable":null},{"type":"function","name":"globalRank","inputs":[],"outputs":[{"name":"","type":"uint256","internalType":"uint256"}],"stateMutability":"view","payable":null},{"type":"function","name":"increaseAllowance","inputs":[{"name":"spender","type":"address","internalType":"address"},{"name":"addedValue","type":"uint256","internalType":"uint256"}],"outputs":[{"name":"","type":"bool","internalType":"bool"}],"stateMutability":"nonpayable","payable":null},{"type":"function","name":"name","inputs":[],"outputs":[{"name":"","type":"string","internalType":"string"}],"stateMutability":"view","payable":null},{"type":"function","name":"stake","inputs":[{"name":"amount","type":"uint256","internalType":"uint256"},{"name":"term","type":"uint256","internalType":"uint256"}],"outputs":[],"stateMutability":"nonpayable","payable":null},{"type":"function","name":"symbol","inputs":[],"outputs":[{"name":"","type":"string","internalType":"string"}],"stateMutability":"view","payable":null},{"type":"function","name":"totalSupply","inputs":[],"outputs":[{"name":"","type":"uint256","internalType":"uint256"}],"stateMutability":"view","payable":null},{"type":"function","name":"totalXenStaked","inputs":[],"outputs":[{"name":"","type":"uint256","internalType":"uint256"}],"stateMutability":"view","payable":null},{"type":"function","name":"transfer","inputs":[{"name":"to","type":"address","internalType":"address"},{"name":"amount","type":"uint256","internalType":"uint256"}],"outputs":[{"name":"","type":"bool","internalType":"bool"}],"stateMutability":"nonpayable","payable":null},{"type":"function","name":"transferFrom","inputs":[{"name":"from","type":"address","internalType":"address"},{"name":"to","type":"address","internalType":"address"},{"name":"amount","type":"uint256","internalType":"uint256"}],"outputs":[{"name":"","type":"bool","internalType":"bool"}],"stateMutability":"nonpayable","payable":null},{"type":"function","name":"userBurns","inputs":[{"name":"","type":"address","internalType":"address"}],"outputs":[{"name":"","type":"uint256","internalType":"uint256"}],"stateMutability":"view","payable":null},{"type":"function","name":"userMints","inputs":[{"name":"","type":"address","internalType":"address"}],"outputs":[{"name":"user","type":"address","internalType":"address"},{"name":"term","type":"uint256","internalType":"uint256"},{"name":"maturityTs","type":"uint256","internalType":"uint256"},{"name":"rank","type":"uint256","internalType":"uint256"},{"name":"amplifier","type":"uint256","internalType":"uint256"},{"name":"eaaRate","type":"uint256","internalType":"uint256"}],"stateMutability":"view","payable":null},{"type":"function","name":"userStakes","inputs":[{"name":"","type":"address","internalType":"address"}],"outputs":[{"name":"term","type":"uint256","internalType":"uint256"},{"name":"maturityTs","type":"uint256","internalType":"uint256"},{"name":"amount","type":"uint256","internalType":"uint256"},{"name":"apy","type":"uint256","internalType":"uint256"}],"stateMutability":"view","payable":null},{"type":"function","name":"withdraw","inputs":[],"outputs":[],"stateMutability":"nonpayable","payable":null},{"type":"event","name":"Approval","inputs":[{"name":"owner","type":"address","indexed":true,"internalType":"address"},{"name":"spender","type":"address","indexed":true,"internalType":"address"},{"name":"value","type":"uint256","indexed":false,"internalType":"uint256"}],"anonymous":false},{"type":"event","name":"MintClaimed","inputs":[{"name":"user","type":"address","indexed":true,"internalType":"address"},{"name":"rewardAmount","type":"uint256","indexed":false,"internalType":"uint256"}],"anonymous":false},{"type":"event","name":"RankClaimed","inputs":[{"name":"user","type":"address","indexed":true,"internalType":"address"},{"name":"term","type":"uint256","indexed":false,"internalType":"uint256"},{"name":"rank","type":"uint256","indexed":false,"internalType":"uint256"}],"anonymous":false},{"type":"event","name":"Staked","inputs":[{"name":"user","type":"address","indexed":true,"internalType":"address"},{"name":"amount","type":"uint256","indexed":false,"internalType":"uint256"},{"name":"term","type":"uint256","indexed":false,"internalType":"uint256"}],"anonymous":false},{"type":"event","name":"Transfer","inputs":[{"name":"from","type":"address","indexed":true,"internalType":"address"},{"name":"to","type":"address","indexed":true,"internalType":"address"},{"name":"value","type":"uint256","indexed":false,"internalType":"uint256"}],"anonymous":false},{"type":"event","name":"Withdrawn","inputs":[{"name":"user","type":"address","indexed":true,"internalType":"address"},{"name":"amount","type":"uint256","indexed":false,"internalType":"uint256"},{"name":"reward","type":"uint256","indexed":false,"internalType":"uint256"}],"anonymous":false}]}