[
  {
    "inputs": [
      {
        "name": "_ANN",
        "type": "uint256"
      },
      {
        "name": "_gamma",
        "type": "uint256"
      },
      {
        "name": "x",
        "type": "uint256[3]"
      },
      {
        "name": "_D",
        "type": "uint256"
      },
      {
        "name": "i",
        "type": "uint256"
      }
    ],
    "name": "get_y",
    "outputs": [
      {
        "name": "",
        "type": "uint256[2]"
      }
    ],
    "stateMutability": "view",
    "type": "function"
  },
  {
    "inputs": [
      {
        "name": "ANN",
        "type": "uint256"
      },
      {
        "name": "gamma",
        "type": "uint256"
      },
      {
        "name": "x_unsorted",
        "type": "uint256[3]"
      }
    ],
    "name": "newton_D",
    "outputs": [
      {
        "name": "",
        "type": "uint256"
      }
    ],
    "stateMutability": "view",
    "type": "function"
  },
  {
    "inputs": [
      {
        "name": "ANN",
        "type": "uint256"
      },
      {
        "name": "gamma",
        "type": "uint256"
      },
      {
        "name": "x_unsorted",
        "type": "uint256[3]"
      },
      {
        "name": "K0_prev",
        "type": "uint256"
      }
    ],
    "name": "newton_D",
    "outputs": [
      {
        "name": "",
        "type": "uint256"
      }
    ],
    "stateMutability": "view",
    "type": "function"
  },
  {
    "inputs": [
      {
        "name": "_xp",
        "type": "uint256[3]"
      },
      {
        "name": "_D",
        "type": "uint256"
      },
      {
        "name": "_A_gamma",
        "type": "uint256[2]"
      }
    ],
    "name": "get_p",
    "outputs": [
      {
        "name": "",
        "type": "uint256[2]"
      }
    ],
    "stateMutability": "view",
    "type": "function"
  },
  {
    "inputs": [
      {
        "name": "x",
        "type": "uint256"
      }
    ],
    "name": "cbrt",
    "outputs": [
      {
        "name": "",
        "type": "uint256"
      }
    ],
    "stateMutability": "view",
    "type": "function"
  },
  {
    "inputs": [
      {
        "name": "_x",
        "type": "uint256[3]"
      }
    ],
    "name": "geometric_mean",
    "outputs": [
      {
        "name": "",
        "type": "uint256"
      }
    ],
    "stateMutability": "view",
    "type": "function"
  },
  {
    "inputs": [
      {
        "name": "x",
        "type": "uint256[3]"
      },
      {
        "name": "fee_gamma",
        "type": "uint256"
      }
    ],
    "name": "reduction_coefficient",
    "outputs": [
      {
        "name": "",
        "type": "uint256"
      }
    ],
    "stateMutability": "view",
    "type": "function"
  },
  {
    "inputs": [
      {
        "name": "_power",
        "type": "int256"
      }
    ],
    "name": "wad_exp",
    "outputs": [
      {
        "name": "",
        "type": "uint256"
      }
    ],
    "stateMutability": "view",
    "type": "function"
  },
  {
    "inputs": [],
    "name": "version",
    "outputs": [
      {
        "name": "",
        "type": "string"
      }
    ],
    "stateMutability": "view",
    "type": "function"
  }
]