{"expiry":1699494171,"data":[{"type":"constructor","inputs":[{"name":"_treasury","type":"address","internalType":"address"},{"name":"_buyFeeNumeratorValue","type":"uint256","internalType":"uint256"},{"name":"_sellFeeNumeratorValue","type":"uint256","internalType":"uint256"}],"stateMutability":"nonpayable","payable":null},{"type":"function","name":"DENOMINATOR","inputs":[],"outputs":[{"name":"","type":"uint256","internalType":"uint256"}],"stateMutability":"view","payable":null},{"type":"function","name":"MAX_BUY_FEE_NUMERATOR","inputs":[],"outputs":[{"name":"","type":"uint256","internalType":"uint256"}],"stateMutability":"view","payable":null},{"type":"function","name":"MAX_SELL_FEE_NUMERATOR","inputs":[],"outputs":[{"name":"","type":"uint256","internalType":"uint256"}],"stateMutability":"view","payable":null},{"type":"function","name":"_sellFeeNumerator","inputs":[],"outputs":[{"name":"","type":"uint256","internalType":"uint256"}],"stateMutability":"view","payable":null},{"type":"function","name":"accountInfo","inputs":[{"name":"","type":"address","internalType":"address"}],"outputs":[{"name":"isLPPool","type":"bool","internalType":"bool"},{"name":"isLiquidityHolder","type":"bool","internalType":"bool"},{"name":"isBlackListed","type":"bool","internalType":"bool"}],"stateMutability":"view","payable":null},{"type":"function","name":"allowance","inputs":[{"name":"owner","type":"address","internalType":"address"},{"name":"spender","type":"address","internalType":"address"}],"outputs":[{"name":"","type":"uint256","internalType":"uint256"}],"stateMutability":"view","payable":null},{"type":"function","name":"approve","inputs":[{"name":"spender","type":"address","internalType":"address"},{"name":"amount","type":"uint256","internalType":"uint256"}],"outputs":[{"name":"","type":"bool","internalType":"bool"}],"stateMutability":"nonpayable","payable":null},{"type":"function","name":"balanceOf","inputs":[{"name":"account","type":"address","internalType":"address"}],"outputs":[{"name":"","type":"uint256","internalType":"uint256"}],"stateMutability":"view","payable":null},{"type":"function","name":"blacklistAddRestrictedForever","inputs":[],"outputs":[{"name":"","type":"bool","internalType":"bool"}],"stateMutability":"view","payable":null},{"type":"function","name":"buyFeeNumerator","inputs":[],"outputs":[{"name":"","type":"uint256","internalType":"uint256"}],"stateMutability":"view","payable":null},{"type":"function","name":"decimals","inputs":[],"outputs":[{"name":"","type":"uint8","internalType":"uint8"}],"stateMutability":"view","payable":null},{"type":"function","name":"decreaseAllowance","inputs":[{"name":"spender","type":"address","internalType":"address"},{"name":"subtractedValue","type":"uint256","internalType":"uint256"}],"outputs":[{"name":"","type":"bool","internalType":"bool"}],"stateMutability":"nonpayable","payable":null},{"type":"function","name":"disableSniperBotProtectionForever","inputs":[],"outputs":[],"stateMutability":"nonpayable","payable":null},{"type":"function","name":"feesAreLockedForever","inputs":[],"outputs":[{"name":"","type":"bool","internalType":"bool"}],"stateMutability":"view","payable":null},{"type":"function","name":"increaseAllowance","inputs":[{"name":"spender","type":"address","internalType":"address"},{"name":"addedValue","type":"uint256","internalType":"uint256"}],"outputs":[{"name":"","type":"bool","internalType":"bool"}],"stateMutability":"nonpayable","payable":null},{"type":"function","name":"lockFeesForever","inputs":[],"outputs":[],"stateMutability":"nonpayable","payable":null},{"type":"function","name":"name","inputs":[],"outputs":[{"name":"","type":"string","internalType":"string"}],"stateMutability":"view","payable":null},{"type":"function","name":"owner","inputs":[],"outputs":[{"name":"","type":"address","internalType":"address"}],"stateMutability":"view","payable":null},{"type":"function","name":"renounceOwnership","inputs":[],"outputs":[],"stateMutability":"nonpayable","payable":null},{"type":"function","name":"restrictBlacklistAddForever","inputs":[],"outputs":[],"stateMutability":"nonpayable","payable":null},{"type":"function","name":"sellFeeNumerator","inputs":[],"outputs":[{"name":"","type":"uint256","internalType":"uint256"}],"stateMutability":"view","payable":null},{"type":"function","name":"setBlacklisted","inputs":[{"name":"account","type":"address","internalType":"address"},{"name":"isBlacklisted","type":"bool","internalType":"bool"}],"outputs":[],"stateMutability":"nonpayable","payable":null},{"type":"function","name":"setBuyFeeNumerator","inputs":[{"name":"value","type":"uint256","internalType":"uint256"}],"outputs":[],"stateMutability":"nonpayable","payable":null},{"type":"function","name":"setLiquidityHolder","inputs":[{"name":"account","type":"address","internalType":"address"},{"name":"flag","type":"bool","internalType":"bool"}],"outputs":[],"stateMutability":"nonpayable","payable":null},{"type":"function","name":"setLpPair","inputs":[{"name":"pair","type":"address","internalType":"address"},{"name":"enabled","type":"bool","internalType":"bool"}],"outputs":[],"stateMutability":"nonpayable","payable":null},{"type":"function","name":"setSellFeeNumerator","inputs":[{"name":"value","type":"uint256","internalType":"uint256"}],"outputs":[],"stateMutability":"nonpayable","payable":null},{"type":"function","name":"setTreasury","inputs":[{"name":"_treasury","type":"address","internalType":"address"}],"outputs":[],"stateMutability":"nonpayable","payable":null},{"type":"function","name":"sniperBotProtectionDisabledForever","inputs":[],"outputs":[{"name":"","type":"bool","internalType":"bool"}],"stateMutability":"view","payable":null},{"type":"function","name":"symbol","inputs":[],"outputs":[{"name":"","type":"string","internalType":"string"}],"stateMutability":"view","payable":null},{"type":"function","name":"totalSupply","inputs":[],"outputs":[{"name":"","type":"uint256","internalType":"uint256"}],"stateMutability":"view","payable":null},{"type":"function","name":"transfer","inputs":[{"name":"to","type":"address","internalType":"address"},{"name":"amount","type":"uint256","internalType":"uint256"}],"outputs":[{"name":"","type":"bool","internalType":"bool"}],"stateMutability":"nonpayable","payable":null},{"type":"function","name":"transferFrom","inputs":[{"name":"from","type":"address","internalType":"address"},{"name":"to","type":"address","internalType":"address"},{"name":"amount","type":"uint256","internalType":"uint256"}],"outputs":[{"name":"","type":"bool","internalType":"bool"}],"stateMutability":"nonpayable","payable":null},{"type":"function","name":"transferOwnership","inputs":[{"name":"newOwner","type":"address","internalType":"address"}],"outputs":[],"stateMutability":"nonpayable","payable":null},{"type":"function","name":"treasury","inputs":[],"outputs":[{"name":"","type":"address","internalType":"address"}],"stateMutability":"view","payable":null},{"type":"event","name":"Approval","inputs":[{"name":"owner","type":"address","indexed":true,"internalType":"address"},{"name":"spender","type":"address","indexed":true,"internalType":"address"},{"name":"value","type":"uint256","indexed":false,"internalType":"uint256"}],"anonymous":false},{"type":"event","name":"BlacklistAddRestrictedForever","inputs":[],"anonymous":false},{"type":"event","name":"BlacklistSet","inputs":[{"name":"account","type":"address","indexed":true,"internalType":"address"},{"name":"flag","type":"bool","indexed":false,"internalType":"bool"}],"anonymous":false},{"type":"event","name":"BuyFeeNumeratorSet","inputs":[{"name":"value","type":"uint256","indexed":false,"internalType":"uint256"}],"anonymous":false},{"type":"event","name":"BuyFeePaid","inputs":[{"name":"from","type":"address","indexed":true,"internalType":"address"},{"name":"to","type":"address","indexed":true,"internalType":"address"},{"name":"amount","type":"uint256","indexed":false,"internalType":"uint256"}],"anonymous":false},{"type":"event","name":"FeesLockedForever","inputs":[],"anonymous":false},{"type":"event","name":"LPPairSet","inputs":[{"name":"pair","type":"address","indexed":true,"internalType":"address"},{"name":"enabled","type":"bool","indexed":false,"internalType":"bool"}],"anonymous":false},{"type":"event","name":"LiquidityHolderSet","inputs":[{"name":"account","type":"address","indexed":true,"internalType":"address"},{"name":"flag","type":"bool","indexed":false,"internalType":"bool"}],"anonymous":false},{"type":"event","name":"OwnershipTransferred","inputs":[{"name":"previousOwner","type":"address","indexed":true,"internalType":"address"},{"name":"newOwner","type":"address","indexed":true,"internalType":"address"}],"anonymous":false},{"type":"event","name":"SellFeeNumeratorSet","inputs":[{"name":"value","type":"uint256","indexed":false,"internalType":"uint256"}],"anonymous":false},{"type":"event","name":"SellFeePaid","inputs":[{"name":"from","type":"address","indexed":true,"internalType":"address"},{"name":"to","type":"address","indexed":true,"internalType":"address"},{"name":"amount","type":"uint256","indexed":false,"internalType":"uint256"}],"anonymous":false},{"type":"event","name":"SniperBotProtectionDisabledForever","inputs":[],"anonymous":false},{"type":"event","name":"Transfer","inputs":[{"name":"from","type":"address","indexed":true,"internalType":"address"},{"name":"to","type":"address","indexed":true,"internalType":"address"},{"name":"value","type":"uint256","indexed":false,"internalType":"uint256"}],"anonymous":false},{"type":"event","name":"TreasurySet","inputs":[{"name":"treasury","type":"address","indexed":false,"internalType":"address"}],"anonymous":false}]}